{
    "lastUpdate": 1728359014685,
    "nextUpdate": 1728445306840,
    "data": {
        "lastNav": "2024-10-04",
        "fund": {
            "proj_id": "M0147_2564",
            "regis_id": "MF0183_2564",
            "regis_date": "2021-06-01",
            "cancel_date": "-",
            "proj_name_th": "กองทุนเปิดเค Sustain ห้ามขายผู้ลงทุนรายย่อย",
            "proj_name_en": "K Sustainable Fund Not for Retail Investors",
            "proj_abbr_name": "K-STN-UI",
            "fund_status": "RG",
            "unique_id": "C0000000021",
            "permit_us_investment": null,
            "invest_country_flag": "1",
            "last_upd_date": "2024-09-20T07:02:31.393"
        },
        "navs": [
            {
                "nav_date": "2024-07-15",
                "unique_id": "C0000000021",
                "class_abbr_name": "K-STN-UI-A(A)",
                "net_asset": 154639035.13,
                "last_val": 8.3971,
                "previous_val": 0,
                "sell_price": 8.4602,
                "buy_price": 8.3971,
                "sell_swap_price": 0,
                "buy_swap_price": 0,
                "remark_th": " ",
                "remark_en": " ",
                "last_upd_date": "2024-07-17T08:04:04.493"
            },
            {
                "nav_date": "2024-07-16",
                "unique_id": "C0000000021",
                "class_abbr_name": "K-STN-UI-A(A)",
                "net_asset": 155148255.82,
                "last_val": 8.4248,
                "previous_val": 0,
                "sell_price": 8.4881,
                "buy_price": 8.4248,
                "sell_swap_price": 0,
                "buy_swap_price": 0,
                "remark_th": " ",
                "remark_en": " ",
                "last_upd_date": "2024-07-18T08:22:27.287"
            },
            {
                "nav_date": "2024-07-17",
                "unique_id": "C0000000021",
                "class_abbr_name": "K-STN-UI-A(A)",
                "net_asset": 149109981.92,
                "last_val": 8.3682,
                "previous_val": 0,
                "sell_price": 8.4311,
                "buy_price": 8.3682,
                "sell_swap_price": 0,
                "buy_swap_price": 0,
                "remark_th": " ",
                "remark_en": " ",
                "last_upd_date": "2024-07-19T08:44:31.75"
            },
            {
                "nav_date": "2024-07-18",
                "unique_id": "C0000000021",
                "class_abbr_name": "K-STN-UI-A(A)",
                "net_asset": 148826829.77,
                "last_val": 8.3523,
                "previous_val": 0,
                "sell_price": 8.415,
                "buy_price": 8.3523,
                "sell_swap_price": 0,
                "buy_swap_price": 0,
                "remark_th": " ",
                "remark_en": " ",
                "last_upd_date": "2024-07-23T08:24:54.193"
            },
            {
                "nav_date": "2024-07-19",
                "unique_id": "C0000000021",
                "class_abbr_name": "K-STN-UI-A(A)",
                "net_asset": 122854753.23,
                "last_val": 8.3517,
                "previous_val": 0,
                "sell_price": 8.4144,
                "buy_price": 8.3517,
                "sell_swap_price": 0,
                "buy_swap_price": 0,
                "remark_th": " ",
                "remark_en": " ",
                "last_upd_date": "2024-07-24T07:27:34.293"
            },
            {
                "nav_date": "2024-07-23",
                "unique_id": "C0000000021",
                "class_abbr_name": "K-STN-UI-A(A)",
                "net_asset": 120656026.47,
                "last_val": 8.3697,
                "previous_val": 0,
                "sell_price": 8.4326,
                "buy_price": 8.3697,
                "sell_swap_price": 0,
                "buy_swap_price": 0,
                "remark_th": " ",
                "remark_en": " ",
                "last_upd_date": "2024-07-25T07:41:44.45"
            },
            {
                "nav_date": "2024-07-24",
                "unique_id": "C0000000021",
                "class_abbr_name": "K-STN-UI-A(A)",
                "net_asset": 120059380,
                "last_val": 8.3283,
                "previous_val": 0,
                "sell_price": 8.3909,
                "buy_price": 8.3283,
                "sell_swap_price": 0,
                "buy_swap_price": 0,
                "remark_th": " ",
                "remark_en": " ",
                "last_upd_date": "2024-07-26T09:06:17.367"
            },
            {
                "nav_date": "2024-07-30",
                "unique_id": "C0000000021",
                "class_abbr_name": "K-STN-UI-A(A)",
                "net_asset": 116192035.18,
                "last_val": 8.3332,
                "previous_val": 0,
                "sell_price": 8.3958,
                "buy_price": 8.3332,
                "sell_swap_price": 0,
                "buy_swap_price": 0,
                "remark_th": " ",
                "remark_en": " ",
                "last_upd_date": "2024-08-01T08:17:23.95"
            },
            {
                "nav_date": "2024-07-31",
                "unique_id": "C0000000021",
                "class_abbr_name": "K-STN-UI-A(A)",
                "net_asset": 116370082.28,
                "last_val": 8.346,
                "previous_val": 0,
                "sell_price": 8.4087,
                "buy_price": 8.346,
                "sell_swap_price": 0,
                "buy_swap_price": 0,
                "remark_th": " ",
                "remark_en": " ",
                "last_upd_date": "2024-08-02T08:41:10.737"
            },
            {
                "nav_date": "2024-08-01",
                "unique_id": "C0000000021",
                "class_abbr_name": "K-STN-UI-A(A)",
                "net_asset": 115536701.03,
                "last_val": 8.2862,
                "previous_val": 0,
                "sell_price": 8.3484,
                "buy_price": 8.2862,
                "sell_swap_price": 0,
                "buy_swap_price": 0,
                "remark_th": " ",
                "remark_en": " ",
                "last_upd_date": "2024-08-05T08:10:55.417"
            },
            {
                "nav_date": "2024-08-02",
                "unique_id": "C0000000021",
                "class_abbr_name": "K-STN-UI-A(A)",
                "net_asset": 114718605.9,
                "last_val": 8.2276,
                "previous_val": 0,
                "sell_price": 8.2894,
                "buy_price": 8.2276,
                "sell_swap_price": 0,
                "buy_swap_price": 0,
                "remark_th": " ",
                "remark_en": " ",
                "last_upd_date": "2024-08-06T08:37:14.91"
            },
            {
                "nav_date": "2024-08-05",
                "unique_id": "C0000000021",
                "class_abbr_name": "K-STN-UI-A(A)",
                "net_asset": 108773148.78,
                "last_val": 8.2002,
                "previous_val": 0,
                "sell_price": 8.2618,
                "buy_price": 8.2002,
                "sell_swap_price": 0,
                "buy_swap_price": 0,
                "remark_th": " ",
                "remark_en": " ",
                "last_upd_date": "2024-08-07T07:25:02.203"
            },
            {
                "nav_date": "2024-08-06",
                "unique_id": "C0000000021",
                "class_abbr_name": "K-STN-UI-A(A)",
                "net_asset": 108795433.81,
                "last_val": 8.2018,
                "previous_val": 0,
                "sell_price": 8.2634,
                "buy_price": 8.2018,
                "sell_swap_price": 0,
                "buy_swap_price": 0,
                "remark_th": " ",
                "remark_en": " ",
                "last_upd_date": "2024-08-09T14:23:57.097"
            },
            {
                "nav_date": "2024-08-07",
                "unique_id": "C0000000021",
                "class_abbr_name": "K-STN-UI-A(A)",
                "net_asset": 108512055.02,
                "last_val": 8.1805,
                "previous_val": 0,
                "sell_price": 8.242,
                "buy_price": 8.1805,
                "sell_swap_price": 0,
                "buy_swap_price": 0,
                "remark_th": " ",
                "remark_en": " ",
                "last_upd_date": "2024-08-13T08:26:48.183"
            },
            {
                "nav_date": "2024-08-08",
                "unique_id": "C0000000021",
                "class_abbr_name": "K-STN-UI-A(A)",
                "net_asset": 108904354.83,
                "last_val": 8.2101,
                "previous_val": 0,
                "sell_price": 8.2718,
                "buy_price": 8.2101,
                "sell_swap_price": 0,
                "buy_swap_price": 0,
                "remark_th": " ",
                "remark_en": " ",
                "last_upd_date": "2024-08-14T08:38:42.82"
            },
            {
                "nav_date": "2024-08-09",
                "unique_id": "C0000000021",
                "class_abbr_name": "K-STN-UI-A(A)",
                "net_asset": 108712170.14,
                "last_val": 8.1956,
                "previous_val": 0,
                "sell_price": 8.2572,
                "buy_price": 8.1956,
                "sell_swap_price": 0,
                "buy_swap_price": 0,
                "remark_th": " ",
                "remark_en": " ",
                "last_upd_date": "2024-08-14T08:38:42.82"
            },
            {
                "nav_date": "2024-08-13",
                "unique_id": "C0000000021",
                "class_abbr_name": "K-STN-UI-A(A)",
                "net_asset": 108866328.3,
                "last_val": 8.2072,
                "previous_val": 0,
                "sell_price": 8.2689,
                "buy_price": 8.2072,
                "sell_swap_price": 0,
                "buy_swap_price": 0,
                "remark_th": " ",
                "remark_en": " ",
                "last_upd_date": "2024-08-16T12:57:58.64"
            },
            {
                "nav_date": "2024-08-14",
                "unique_id": "C0000000021",
                "class_abbr_name": "K-STN-UI-A(A)",
                "net_asset": 108700382.12,
                "last_val": 8.1947,
                "previous_val": 0,
                "sell_price": 8.2563,
                "buy_price": 8.1947,
                "sell_swap_price": 0,
                "buy_swap_price": 0,
                "remark_th": " ",
                "remark_en": " ",
                "last_upd_date": "2024-08-19T08:41:33.007"
            },
            {
                "nav_date": "2024-08-15",
                "unique_id": "C0000000021",
                "class_abbr_name": "K-STN-UI-A(A)",
                "net_asset": 109110781.98,
                "last_val": 8.2256,
                "previous_val": 0,
                "sell_price": 8.2874,
                "buy_price": 8.2256,
                "sell_swap_price": 0,
                "buy_swap_price": 0,
                "remark_th": " ",
                "remark_en": " ",
                "last_upd_date": "2024-08-20T08:35:09.247"
            },
            {
                "nav_date": "2024-08-16",
                "unique_id": "C0000000021",
                "class_abbr_name": "K-STN-UI-A(A)",
                "net_asset": 109194898.93,
                "last_val": 8.232,
                "previous_val": 0,
                "sell_price": 8.2938,
                "buy_price": 8.232,
                "sell_swap_price": 0,
                "buy_swap_price": 0,
                "remark_th": " ",
                "remark_en": " ",
                "last_upd_date": "2024-08-20T08:35:09.247"
            },
            {
                "nav_date": "2024-08-19",
                "unique_id": "C0000000021",
                "class_abbr_name": "K-STN-UI-A(A)",
                "net_asset": 109158999.53,
                "last_val": 8.2292,
                "previous_val": 0,
                "sell_price": 8.291,
                "buy_price": 8.2292,
                "sell_swap_price": 0,
                "buy_swap_price": 0,
                "remark_th": " ",
                "remark_en": " ",
                "last_upd_date": "2024-08-21T08:01:08.107"
            },
            {
                "nav_date": "2024-08-20",
                "unique_id": "C0000000021",
                "class_abbr_name": "K-STN-UI-A(A)",
                "net_asset": 108793977.53,
                "last_val": 8.2017,
                "previous_val": 0,
                "sell_price": 8.2633,
                "buy_price": 8.2017,
                "sell_swap_price": 0,
                "buy_swap_price": 0,
                "remark_th": " ",
                "remark_en": " ",
                "last_upd_date": "2024-08-23T08:38:42.927"
            },
            {
                "nav_date": "2024-08-21",
                "unique_id": "C0000000021",
                "class_abbr_name": "K-STN-UI-A(A)",
                "net_asset": 109283518.85,
                "last_val": 8.2386,
                "previous_val": 0,
                "sell_price": 8.3005,
                "buy_price": 8.2386,
                "sell_swap_price": 0,
                "buy_swap_price": 0,
                "remark_th": " ",
                "remark_en": " ",
                "last_upd_date": "2024-08-26T08:41:33.223"
            },
            {
                "nav_date": "2024-08-22",
                "unique_id": "C0000000021",
                "class_abbr_name": "K-STN-UI-A(A)",
                "net_asset": 108143446.06,
                "last_val": 8.2193,
                "previous_val": 0,
                "sell_price": 8.281,
                "buy_price": 8.2193,
                "sell_swap_price": 0,
                "buy_swap_price": 0,
                "remark_th": " ",
                "remark_en": " ",
                "last_upd_date": "2024-08-27T07:44:20.403"
            },
            {
                "nav_date": "2024-08-23",
                "unique_id": "C0000000021",
                "class_abbr_name": "K-STN-UI-A(A)",
                "net_asset": 108626654.6,
                "last_val": 8.256,
                "previous_val": 0,
                "sell_price": 8.318,
                "buy_price": 8.256,
                "sell_swap_price": 0,
                "buy_swap_price": 0,
                "remark_th": " ",
                "remark_en": " ",
                "last_upd_date": "2024-08-28T08:09:57.097"
            },
            {
                "nav_date": "2024-08-26",
                "unique_id": "C0000000021",
                "class_abbr_name": "K-STN-UI-A(A)",
                "net_asset": 108308009.44,
                "last_val": 8.2318,
                "previous_val": 0,
                "sell_price": 8.2936,
                "buy_price": 8.2318,
                "sell_swap_price": 0,
                "buy_swap_price": 0,
                "remark_th": " ",
                "remark_en": " ",
                "last_upd_date": "2024-08-28T08:09:57.097"
            },
            {
                "nav_date": "2024-08-27",
                "unique_id": "C0000000021",
                "class_abbr_name": "K-STN-UI-A(A)",
                "net_asset": 108462087.32,
                "last_val": 8.2435,
                "previous_val": 0,
                "sell_price": 8.3054,
                "buy_price": 8.2435,
                "sell_swap_price": 0,
                "buy_swap_price": 0,
                "remark_th": " ",
                "remark_en": " ",
                "last_upd_date": "2024-08-30T08:38:58.973"
            },
            {
                "nav_date": "2024-08-28",
                "unique_id": "C0000000021",
                "class_abbr_name": "K-STN-UI-A(A)",
                "net_asset": 107512815.85,
                "last_val": 8.2312,
                "previous_val": 0,
                "sell_price": 8.293,
                "buy_price": 8.2312,
                "sell_swap_price": 0,
                "buy_swap_price": 0,
                "remark_th": " ",
                "remark_en": " ",
                "last_upd_date": "2024-09-02T08:37:01.663"
            },
            {
                "nav_date": "2024-08-29",
                "unique_id": "C0000000021",
                "class_abbr_name": "K-STN-UI-A(A)",
                "net_asset": 106763761.85,
                "last_val": 8.2417,
                "previous_val": 0,
                "sell_price": 8.3036,
                "buy_price": 8.2417,
                "sell_swap_price": 0,
                "buy_swap_price": 0,
                "remark_th": " ",
                "remark_en": " ",
                "last_upd_date": "2024-09-03T23:16:04.11"
            },
            {
                "nav_date": "2024-08-30",
                "unique_id": "C0000000021",
                "class_abbr_name": "K-STN-UI-A(A)",
                "net_asset": 106862280.35,
                "last_val": 8.2493,
                "previous_val": 0,
                "sell_price": 8.3113,
                "buy_price": 8.2493,
                "sell_swap_price": 0,
                "buy_swap_price": 0,
                "remark_th": " ",
                "remark_en": " ",
                "last_upd_date": "2024-09-03T23:16:04.11"
            },
            {
                "nav_date": "2024-09-03",
                "unique_id": "C0000000021",
                "class_abbr_name": "K-STN-UI-A(A)",
                "net_asset": 106376556.37,
                "last_val": 8.2118,
                "previous_val": 0,
                "sell_price": 8.2735,
                "buy_price": 8.2118,
                "sell_swap_price": 0,
                "buy_swap_price": 0,
                "remark_th": " ",
                "remark_en": " ",
                "last_upd_date": "2024-09-06T08:34:45.66"
            },
            {
                "nav_date": "2024-09-04",
                "unique_id": "C0000000021",
                "class_abbr_name": "K-STN-UI-A(A)",
                "net_asset": 106338596.3,
                "last_val": 8.2088,
                "previous_val": 0,
                "sell_price": 8.2705,
                "buy_price": 8.2088,
                "sell_swap_price": 0,
                "buy_swap_price": 0,
                "remark_th": " ",
                "remark_en": " ",
                "last_upd_date": "2024-09-09T08:37:08.263"
            },
            {
                "nav_date": "2024-09-05",
                "unique_id": "C0000000021",
                "class_abbr_name": "K-STN-UI-A(A)",
                "net_asset": 105308268.29,
                "last_val": 8.1973,
                "previous_val": 0,
                "sell_price": 8.2589,
                "buy_price": 8.1973,
                "sell_swap_price": 0,
                "buy_swap_price": 0,
                "remark_th": " ",
                "remark_en": " ",
                "last_upd_date": "2024-09-10T08:22:47.723"
            },
            {
                "nav_date": "2024-09-09",
                "unique_id": "C0000000021",
                "class_abbr_name": "K-STN-UI-A(A)",
                "net_asset": 105260187.17,
                "last_val": 8.1935,
                "previous_val": 0,
                "sell_price": 8.2551,
                "buy_price": 8.1935,
                "sell_swap_price": 0,
                "buy_swap_price": 0,
                "remark_th": " ",
                "remark_en": " ",
                "last_upd_date": "2024-09-12T09:50:42.967"
            },
            {
                "nav_date": "2024-09-10",
                "unique_id": "C0000000021",
                "class_abbr_name": "K-STN-UI-A(A)",
                "net_asset": 105058424.1,
                "last_val": 8.1778,
                "previous_val": 0,
                "sell_price": 8.2392,
                "buy_price": 8.1778,
                "sell_swap_price": 0,
                "buy_swap_price": 0,
                "remark_th": " ",
                "remark_en": " ",
                "last_upd_date": "2024-09-13T08:45:35.953"
            },
            {
                "nav_date": "2024-09-11",
                "unique_id": "C0000000021",
                "class_abbr_name": "K-STN-UI-A(A)",
                "net_asset": 105220359.57,
                "last_val": 8.1904,
                "previous_val": 0,
                "sell_price": 8.2519,
                "buy_price": 8.1904,
                "sell_swap_price": 0,
                "buy_swap_price": 0,
                "remark_th": " ",
                "remark_en": " ",
                "last_upd_date": "2024-09-16T08:36:06.01"
            },
            {
                "nav_date": "2024-09-12",
                "unique_id": "C0000000021",
                "class_abbr_name": "K-STN-UI-A(A)",
                "net_asset": 104063148.52,
                "last_val": 8.2007,
                "previous_val": 0,
                "sell_price": 8.2623,
                "buy_price": 8.2007,
                "sell_swap_price": 0,
                "buy_swap_price": 0,
                "remark_th": " ",
                "remark_en": " ",
                "last_upd_date": "2024-09-17T08:21:18.21"
            },
            {
                "nav_date": "2024-09-13",
                "unique_id": "C0000000021",
                "class_abbr_name": "K-STN-UI-A(A)",
                "net_asset": 104063722.44,
                "last_val": 8.2007,
                "previous_val": 0,
                "sell_price": 8.2623,
                "buy_price": 8.2007,
                "sell_swap_price": 0,
                "buy_swap_price": 0,
                "remark_th": " ",
                "remark_en": " ",
                "last_upd_date": "2024-09-18T09:26:21.943"
            },
            {
                "nav_date": "2024-09-16",
                "unique_id": "C0000000021",
                "class_abbr_name": "K-STN-UI-A(A)",
                "net_asset": 104133973.25,
                "last_val": 8.2063,
                "previous_val": 0,
                "sell_price": 8.2679,
                "buy_price": 8.2063,
                "sell_swap_price": 0,
                "buy_swap_price": 0,
                "remark_th": " ",
                "remark_en": " ",
                "last_upd_date": "2024-09-19T07:37:05.253"
            },
            {
                "nav_date": "2024-09-17",
                "unique_id": "C0000000021",
                "class_abbr_name": "K-STN-UI-A(A)",
                "net_asset": 104152048.58,
                "last_val": 8.2077,
                "previous_val": 0,
                "sell_price": 8.2694,
                "buy_price": 8.2077,
                "sell_swap_price": 0,
                "buy_swap_price": 0,
                "remark_th": " ",
                "remark_en": " ",
                "last_upd_date": "2024-09-20T08:42:26.373"
            },
            {
                "nav_date": "2024-09-23",
                "unique_id": "C0000000021",
                "class_abbr_name": "K-STN-UI-A(A)",
                "net_asset": 103432163.3,
                "last_val": 8.2206,
                "previous_val": 0,
                "sell_price": 8.2824,
                "buy_price": 8.2206,
                "sell_swap_price": 0,
                "buy_swap_price": 0,
                "remark_th": " ",
                "remark_en": " ",
                "last_upd_date": "2024-09-26T07:48:57.42"
            },
            {
                "nav_date": "2024-09-24",
                "unique_id": "C0000000021",
                "class_abbr_name": "K-STN-UI-A(A)",
                "net_asset": 103633004.28,
                "last_val": 8.2365,
                "previous_val": 0,
                "sell_price": 8.2984,
                "buy_price": 8.2365,
                "sell_swap_price": 0,
                "buy_swap_price": 0,
                "remark_th": " ",
                "remark_en": " ",
                "last_upd_date": "2024-09-27T08:40:14.763"
            },
            {
                "nav_date": "2024-09-25",
                "unique_id": "C0000000021",
                "class_abbr_name": "K-STN-UI-A(A)",
                "net_asset": 102863898.06,
                "last_val": 8.1754,
                "previous_val": 0,
                "sell_price": 8.2368,
                "buy_price": 8.1754,
                "sell_swap_price": 0,
                "buy_swap_price": 0,
                "remark_th": " ",
                "remark_en": " ",
                "last_upd_date": "2024-09-30T08:15:58.27"
            },
            {
                "nav_date": "2024-09-26",
                "unique_id": "C0000000021",
                "class_abbr_name": "K-STN-UI-A(A)",
                "net_asset": 102433132.78,
                "last_val": 8.2113,
                "previous_val": 0,
                "sell_price": 8.273,
                "buy_price": 8.2113,
                "sell_swap_price": 0,
                "buy_swap_price": 0,
                "remark_th": " ",
                "remark_en": " ",
                "last_upd_date": "2024-10-01T07:38:55.78"
            },
            {
                "nav_date": "2024-09-27",
                "unique_id": "C0000000021",
                "class_abbr_name": "K-STN-UI-A(A)",
                "net_asset": 102661380.02,
                "last_val": 8.2296,
                "previous_val": 0,
                "sell_price": 8.2914,
                "buy_price": 8.2296,
                "sell_swap_price": 0,
                "buy_swap_price": 0,
                "remark_th": " ",
                "remark_en": " ",
                "last_upd_date": "2024-10-02T08:24:23.163"
            },
            {
                "nav_date": "2024-09-30",
                "unique_id": "C0000000021",
                "class_abbr_name": "K-STN-UI-A(A)",
                "net_asset": 102451401.07,
                "last_val": 8.2127,
                "previous_val": 0,
                "sell_price": 8.2744,
                "buy_price": 8.2127,
                "sell_swap_price": 0,
                "buy_swap_price": 0,
                "remark_th": " ",
                "remark_en": " ",
                "last_upd_date": "2024-10-03T08:50:21.037"
            },
            {
                "nav_date": "2024-10-02",
                "unique_id": "C0000000021",
                "class_abbr_name": "K-STN-UI-A(A)",
                "net_asset": 102314972.32,
                "last_val": 8.2018,
                "previous_val": 0,
                "sell_price": 8.2634,
                "buy_price": 8.2018,
                "sell_swap_price": 0,
                "buy_swap_price": 0,
                "remark_th": " ",
                "remark_en": " ",
                "last_upd_date": "2024-10-07T08:31:47.35"
            },
            {
                "nav_date": "2024-10-03",
                "unique_id": "C0000000021",
                "class_abbr_name": "K-STN-UI-A(A)",
                "net_asset": 102206538.78,
                "last_val": 8.1931,
                "previous_val": 0,
                "sell_price": 8.2546,
                "buy_price": 8.1931,
                "sell_swap_price": 0,
                "buy_swap_price": 0,
                "remark_th": " ",
                "remark_en": " ",
                "last_upd_date": "2024-10-08T07:43:58.373"
            },
            {
                "nav_date": "2024-10-04",
                "unique_id": "C0000000021",
                "class_abbr_name": "K-STN-UI-A(A)",
                "net_asset": 102291032.73,
                "last_val": 8.1999,
                "previous_val": 0,
                "sell_price": 8.2615,
                "buy_price": 8.1999,
                "sell_swap_price": 0,
                "buy_swap_price": 0,
                "remark_th": " ",
                "remark_en": " ",
                "last_upd_date": "2024-10-08T07:43:58.373"
            }
        ]
    }
}