{
    "lastUpdate": 1764473759562,
    "nextUpdate": 1764560159562,
    "data": {
        "lastNav": "2025-11-26",
        "fund": {
            "proj_id": "M0537_2568",
            "regis_id": "MF0471_2568",
            "regis_date": "2025-08-29",
            "cancel_date": "-",
            "proj_name_th": "กองทุนเปิดเคเคพี โกลบอล บาลานซ์ อโลเคชั่น ห้ามขายผู้ลงทุนรายย่อย",
            "proj_name_en": "KKP GLOBAL BALANCED ALLOCATION FUND NOT FOR RETAIL INVESTORS",
            "proj_abbr_name": "KKP GBA-UI FUND",
            "fund_status": "RG",
            "unique_id": "C0000005025",
            "permit_us_investment": null,
            "invest_country_flag": "1",
            "last_upd_date": "2025-11-14T09:39:17.42"
        },
        "navs": [
            {
                "nav_date": "2025-08-29",
                "unique_id": "C0000005025",
                "class_abbr_name": "KKP GBA-UI-M",
                "net_asset": 666633536,
                "last_val": 9.9972,
                "previous_val": 0,
                "sell_price": 9.9973,
                "buy_price": 9.9972,
                "sell_swap_price": 9.9972,
                "buy_swap_price": 9.9973,
                "remark_th": " ",
                "remark_en": " ",
                "last_upd_date": "2025-09-04T16:10:12.2"
            },
            {
                "nav_date": "2025-09-02",
                "unique_id": "C0000005025",
                "class_abbr_name": "KKP GBA-UI-M",
                "net_asset": 662091008,
                "last_val": 9.9291,
                "previous_val": 0,
                "sell_price": 9.9292,
                "buy_price": 9.9291,
                "sell_swap_price": 9.9291,
                "buy_swap_price": 9.9292,
                "remark_th": " ",
                "remark_en": " ",
                "last_upd_date": "2025-09-05T16:05:25.647"
            },
            {
                "nav_date": "2025-09-08",
                "unique_id": "C0000005025",
                "class_abbr_name": "KKP GBA-UI-M",
                "net_asset": 762021120,
                "last_val": 10.0453,
                "previous_val": 0,
                "sell_price": 10.0454,
                "buy_price": 10.0453,
                "sell_swap_price": 10.0453,
                "buy_swap_price": 10.0454,
                "remark_th": " ",
                "remark_en": " ",
                "last_upd_date": "2025-09-11T16:04:37.577"
            },
            {
                "nav_date": "2025-09-09",
                "unique_id": "C0000005025",
                "class_abbr_name": "KKP GBA-UI-M",
                "net_asset": 761331648,
                "last_val": 10.0363,
                "previous_val": 0,
                "sell_price": 10.0364,
                "buy_price": 10.0363,
                "sell_swap_price": 10.0363,
                "buy_swap_price": 10.0364,
                "remark_th": " ",
                "remark_en": " ",
                "last_upd_date": "2025-09-12T16:07:03.06"
            },
            {
                "nav_date": "2025-09-10",
                "unique_id": "C0000005025",
                "class_abbr_name": "KKP GBA-UI-M",
                "net_asset": 767850880,
                "last_val": 10.0746,
                "previous_val": 0,
                "sell_price": 10.0747,
                "buy_price": 10.0746,
                "sell_swap_price": 10.0746,
                "buy_swap_price": 10.0747,
                "remark_th": " ",
                "remark_en": " ",
                "last_upd_date": "2025-09-15T21:02:46.33"
            },
            {
                "nav_date": "2025-09-11",
                "unique_id": "C0000005025",
                "class_abbr_name": "KKP GBA-UI-M",
                "net_asset": 773092608,
                "last_val": 10.1262,
                "previous_val": 0,
                "sell_price": 10.1263,
                "buy_price": 10.1262,
                "sell_swap_price": 10.1262,
                "buy_swap_price": 10.1263,
                "remark_th": " ",
                "remark_en": " ",
                "last_upd_date": "2025-09-16T16:05:07.967"
            },
            {
                "nav_date": "2025-09-12",
                "unique_id": "C0000005025",
                "class_abbr_name": "KKP GBA-UI-M",
                "net_asset": 771698368,
                "last_val": 10.108,
                "previous_val": 0,
                "sell_price": 10.1081,
                "buy_price": 10.108,
                "sell_swap_price": 10.108,
                "buy_swap_price": 10.1081,
                "remark_th": " ",
                "remark_en": " ",
                "last_upd_date": "2025-09-18T16:07:34.377"
            },
            {
                "nav_date": "2025-09-16",
                "unique_id": "C0000005025",
                "class_abbr_name": "KKP GBA-UI-M",
                "net_asset": 784102976,
                "last_val": 10.1283,
                "previous_val": 0,
                "sell_price": 10.1284,
                "buy_price": 10.1283,
                "sell_swap_price": 10.1283,
                "buy_swap_price": 10.1284,
                "remark_th": " ",
                "remark_en": " ",
                "last_upd_date": "2025-09-19T16:06:56.593"
            },
            {
                "nav_date": "2025-09-17",
                "unique_id": "C0000005025",
                "class_abbr_name": "KKP GBA-UI-M",
                "net_asset": 1838525312,
                "last_val": 10.1297,
                "previous_val": 0,
                "sell_price": 10.1298,
                "buy_price": 10.1297,
                "sell_swap_price": 10.1297,
                "buy_swap_price": 10.1298,
                "remark_th": " ",
                "remark_en": " ",
                "last_upd_date": "2025-09-22T16:06:08.723"
            },
            {
                "nav_date": "2025-09-18",
                "unique_id": "C0000005025",
                "class_abbr_name": "KKP GBA-UI-M",
                "net_asset": 1839717120,
                "last_val": 10.1362,
                "previous_val": 0,
                "sell_price": 10.1363,
                "buy_price": 10.1362,
                "sell_swap_price": 10.1362,
                "buy_swap_price": 10.1363,
                "remark_th": " ",
                "remark_en": " ",
                "last_upd_date": "2025-09-23T16:05:27.16"
            },
            {
                "nav_date": "2025-09-22",
                "unique_id": "C0000005025",
                "class_abbr_name": "KKP GBA-UI-M",
                "net_asset": 1841648000,
                "last_val": 10.1469,
                "previous_val": 0,
                "sell_price": 10.147,
                "buy_price": 10.1469,
                "sell_swap_price": 10.1469,
                "buy_swap_price": 10.147,
                "remark_th": " ",
                "remark_en": " ",
                "last_upd_date": "2025-09-26T16:07:51.863"
            },
            {
                "nav_date": "2025-09-24",
                "unique_id": "C0000005025",
                "class_abbr_name": "KKP GBA-UI-M",
                "net_asset": 1839272320,
                "last_val": 10.1338,
                "previous_val": 0,
                "sell_price": 10.1339,
                "buy_price": 10.1338,
                "sell_swap_price": 10.1338,
                "buy_swap_price": 10.1339,
                "remark_th": " ",
                "remark_en": " ",
                "last_upd_date": "2025-09-29T16:05:07.487"
            },
            {
                "nav_date": "2025-09-25",
                "unique_id": "C0000005025",
                "class_abbr_name": "KKP GBA-UI-M",
                "net_asset": 1828195584,
                "last_val": 10.0851,
                "previous_val": 0,
                "sell_price": 10.0852,
                "buy_price": 10.0851,
                "sell_swap_price": 10.0851,
                "buy_swap_price": 10.0852,
                "remark_th": " ",
                "remark_en": " ",
                "last_upd_date": "2025-09-30T16:07:44.08"
            },
            {
                "nav_date": "2025-09-26",
                "unique_id": "C0000005025",
                "class_abbr_name": "KKP GBA-UI-M",
                "net_asset": 1836091136,
                "last_val": 10.1286,
                "previous_val": 0,
                "sell_price": 10.1287,
                "buy_price": 10.1286,
                "sell_swap_price": 10.1286,
                "buy_swap_price": 10.1287,
                "remark_th": " ",
                "remark_en": " ",
                "last_upd_date": "2025-10-01T16:07:06.003"
            },
            {
                "nav_date": "2025-09-29",
                "unique_id": "C0000005025",
                "class_abbr_name": "KKP GBA-UI-M",
                "net_asset": 1843536000,
                "last_val": 10.1697,
                "previous_val": 0,
                "sell_price": 10.1698,
                "buy_price": 10.1697,
                "sell_swap_price": 10.1697,
                "buy_swap_price": 10.1698,
                "remark_th": " ",
                "remark_en": " ",
                "last_upd_date": "2025-10-02T21:09:28.88"
            },
            {
                "nav_date": "2025-09-30",
                "unique_id": "C0000005025",
                "class_abbr_name": "KKP GBA-UI-M",
                "net_asset": 2680100096,
                "last_val": 10.198,
                "previous_val": 0,
                "sell_price": 10.1981,
                "buy_price": 10.198,
                "sell_swap_price": 10.198,
                "buy_swap_price": 10.1981,
                "remark_th": " ",
                "remark_en": " ",
                "last_upd_date": "2025-10-03T16:07:06.887"
            },
            {
                "nav_date": "2025-10-01",
                "unique_id": "C0000005025",
                "class_abbr_name": "KKP GBA-UI-M",
                "net_asset": 2688541696,
                "last_val": 10.2301,
                "previous_val": 0,
                "sell_price": 10.2302,
                "buy_price": 10.2301,
                "sell_swap_price": 10.2301,
                "buy_swap_price": 10.2302,
                "remark_th": " ",
                "remark_en": " ",
                "last_upd_date": "2025-10-06T16:10:03.587"
            },
            {
                "nav_date": "2025-10-02",
                "unique_id": "C0000005025",
                "class_abbr_name": "KKP GBA-UI-M",
                "net_asset": 3056113152,
                "last_val": 10.2519,
                "previous_val": 0,
                "sell_price": 10.252,
                "buy_price": 10.2519,
                "sell_swap_price": 10.2519,
                "buy_swap_price": 10.252,
                "remark_th": " ",
                "remark_en": " ",
                "last_upd_date": "2025-10-10T16:07:56.043"
            },
            {
                "nav_date": "2025-10-08",
                "unique_id": "C0000005025",
                "class_abbr_name": "KKP GBA-UI-M",
                "net_asset": 3063547648,
                "last_val": 10.2769,
                "previous_val": 0,
                "sell_price": 10.277,
                "buy_price": 10.2769,
                "sell_swap_price": 10.2769,
                "buy_swap_price": 10.277,
                "remark_th": " ",
                "remark_en": " ",
                "last_upd_date": "2025-10-14T16:12:13.483"
            },
            {
                "nav_date": "2025-10-09",
                "unique_id": "C0000005025",
                "class_abbr_name": "KKP GBA-UI-M",
                "net_asset": 3246780160,
                "last_val": 10.2655,
                "previous_val": 0,
                "sell_price": 10.2656,
                "buy_price": 10.2655,
                "sell_swap_price": 10.2655,
                "buy_swap_price": 10.2656,
                "remark_th": " ",
                "remark_en": " ",
                "last_upd_date": "2025-10-15T21:08:05.88"
            },
            {
                "nav_date": "2025-10-10",
                "unique_id": "C0000005025",
                "class_abbr_name": "KKP GBA-UI-M",
                "net_asset": 3221546752,
                "last_val": 10.1857,
                "previous_val": 0,
                "sell_price": 10.1858,
                "buy_price": 10.1857,
                "sell_swap_price": 10.1857,
                "buy_swap_price": 10.1858,
                "remark_th": " ",
                "remark_en": " ",
                "last_upd_date": "2025-10-16T16:06:32.617"
            },
            {
                "nav_date": "2025-10-14",
                "unique_id": "C0000005025",
                "class_abbr_name": "KKP GBA-UI-M",
                "net_asset": 3317967104,
                "last_val": 10.201,
                "previous_val": 0,
                "sell_price": 10.2011,
                "buy_price": 10.201,
                "sell_swap_price": 10.201,
                "buy_swap_price": 10.2011,
                "remark_th": " ",
                "remark_en": " ",
                "last_upd_date": "2025-10-17T16:10:48.08"
            },
            {
                "nav_date": "2025-10-15",
                "unique_id": "C0000005025",
                "class_abbr_name": "KKP GBA-UI-M",
                "net_asset": 3332280576,
                "last_val": 10.245,
                "previous_val": 0,
                "sell_price": 10.2451,
                "buy_price": 10.245,
                "sell_swap_price": 10.245,
                "buy_swap_price": 10.2451,
                "remark_th": " ",
                "remark_en": " ",
                "last_upd_date": "2025-10-20T16:05:15.49"
            },
            {
                "nav_date": "2025-10-16",
                "unique_id": "C0000005025",
                "class_abbr_name": "KKP GBA-UI-M",
                "net_asset": 3342942464,
                "last_val": 10.2433,
                "previous_val": 0,
                "sell_price": 10.2434,
                "buy_price": 10.2433,
                "sell_swap_price": 10.2433,
                "buy_swap_price": 10.2434,
                "remark_th": " ",
                "remark_en": " ",
                "last_upd_date": "2025-10-21T16:09:46.947"
            },
            {
                "nav_date": "2025-10-17",
                "unique_id": "C0000005025",
                "class_abbr_name": "KKP GBA-UI-M",
                "net_asset": 3342987264,
                "last_val": 10.2434,
                "previous_val": 0,
                "sell_price": 10.2435,
                "buy_price": 10.2434,
                "sell_swap_price": 10.2434,
                "buy_swap_price": 10.2435,
                "remark_th": " ",
                "remark_en": " ",
                "last_upd_date": "2025-10-22T08:16:07.113"
            },
            {
                "nav_date": "2025-10-20",
                "unique_id": "C0000005025",
                "class_abbr_name": "KKP GBA-UI-M",
                "net_asset": 3432073728,
                "last_val": 10.3258,
                "previous_val": 0,
                "sell_price": 10.3259,
                "buy_price": 10.3258,
                "sell_swap_price": 10.3258,
                "buy_swap_price": 10.3259,
                "remark_th": " ",
                "remark_en": " ",
                "last_upd_date": "2025-10-24T16:05:37.397"
            },
            {
                "nav_date": "2025-10-21",
                "unique_id": "C0000005025",
                "class_abbr_name": "KKP GBA-UI-M",
                "net_asset": 3434874112,
                "last_val": 10.3343,
                "previous_val": 0,
                "sell_price": 10.3344,
                "buy_price": 10.3343,
                "sell_swap_price": 10.3343,
                "buy_swap_price": 10.3344,
                "remark_th": " ",
                "remark_en": " ",
                "last_upd_date": "2025-10-27T16:07:28.94"
            },
            {
                "nav_date": "2025-10-22",
                "unique_id": "C0000005025",
                "class_abbr_name": "KKP GBA-UI-M",
                "net_asset": 3431136000,
                "last_val": 10.323,
                "previous_val": 0,
                "sell_price": 10.3231,
                "buy_price": 10.323,
                "sell_swap_price": 10.323,
                "buy_swap_price": 10.3231,
                "remark_th": " ",
                "remark_en": " ",
                "last_upd_date": "2025-10-28T16:08:39.847"
            },
            {
                "nav_date": "2025-10-24",
                "unique_id": "C0000005025",
                "class_abbr_name": "KKP GBA-UI-M",
                "net_asset": 3521703680,
                "last_val": 10.3736,
                "previous_val": 0,
                "sell_price": 10.3737,
                "buy_price": 10.3736,
                "sell_swap_price": 10.3736,
                "buy_swap_price": 10.3737,
                "remark_th": " ",
                "remark_en": " ",
                "last_upd_date": "2025-10-30T16:06:59.56"
            },
            {
                "nav_date": "2025-10-28",
                "unique_id": "C0000005025",
                "class_abbr_name": "KKP GBA-UI-M",
                "net_asset": 4551453696,
                "last_val": 10.4145,
                "previous_val": 0,
                "sell_price": 10.4146,
                "buy_price": 10.4145,
                "sell_swap_price": 10.4145,
                "buy_swap_price": 10.4146,
                "remark_th": " ",
                "remark_en": " ",
                "last_upd_date": "2025-10-31T16:10:38.673"
            },
            {
                "nav_date": "2025-10-29",
                "unique_id": "C0000005025",
                "class_abbr_name": "KKP GBA-UI-M",
                "net_asset": 4611893248,
                "last_val": 10.3838,
                "previous_val": 0,
                "sell_price": 10.3839,
                "buy_price": 10.3838,
                "sell_swap_price": 10.3838,
                "buy_swap_price": 10.3839,
                "remark_th": " ",
                "remark_en": " ",
                "last_upd_date": "2025-11-03T16:07:47.003"
            },
            {
                "nav_date": "2025-10-30",
                "unique_id": "C0000005025",
                "class_abbr_name": "KKP GBA-UI-M",
                "net_asset": 4680369664,
                "last_val": 10.3361,
                "previous_val": 0,
                "sell_price": 10.3362,
                "buy_price": 10.3361,
                "sell_swap_price": 10.3361,
                "buy_swap_price": 10.3362,
                "remark_th": " ",
                "remark_en": " ",
                "last_upd_date": "2025-11-04T16:06:34.707"
            },
            {
                "nav_date": "2025-10-31",
                "unique_id": "C0000005025",
                "class_abbr_name": "KKP GBA-UI-M",
                "net_asset": 4683856384,
                "last_val": 10.3254,
                "previous_val": 0,
                "sell_price": 10.3255,
                "buy_price": 10.3254,
                "sell_swap_price": 10.3254,
                "buy_swap_price": 10.3255,
                "remark_th": " ",
                "remark_en": " ",
                "last_upd_date": "2025-11-06T16:10:41.603"
            },
            {
                "nav_date": "2025-11-04",
                "unique_id": "C0000005025",
                "class_abbr_name": "KKP GBA-UI-M",
                "net_asset": 4698533376,
                "last_val": 10.281,
                "previous_val": 0,
                "sell_price": 10.2811,
                "buy_price": 10.281,
                "sell_swap_price": 10.281,
                "buy_swap_price": 10.2811,
                "remark_th": " ",
                "remark_en": " ",
                "last_upd_date": "2025-11-07T16:06:39.46"
            },
            {
                "nav_date": "2025-11-05",
                "unique_id": "C0000005025",
                "class_abbr_name": "KKP GBA-UI-M",
                "net_asset": 4705886208,
                "last_val": 10.2826,
                "previous_val": 0,
                "sell_price": 10.2827,
                "buy_price": 10.2826,
                "sell_swap_price": 10.2826,
                "buy_swap_price": 10.2827,
                "remark_th": " ",
                "remark_en": " ",
                "last_upd_date": "2025-11-10T16:05:52.2"
            },
            {
                "nav_date": "2025-11-06",
                "unique_id": "C0000005025",
                "class_abbr_name": "KKP GBA-UI-M",
                "net_asset": 4757530624,
                "last_val": 10.2348,
                "previous_val": 0,
                "sell_price": 10.2349,
                "buy_price": 10.2348,
                "sell_swap_price": 10.2348,
                "buy_swap_price": 10.2349,
                "remark_th": " ",
                "remark_en": " ",
                "last_upd_date": "2025-11-11T16:09:59.097"
            },
            {
                "nav_date": "2025-11-07",
                "unique_id": "C0000005025",
                "class_abbr_name": "KKP GBA-UI-M",
                "net_asset": 4754188288,
                "last_val": 10.2148,
                "previous_val": 0,
                "sell_price": 10.2149,
                "buy_price": 10.2148,
                "sell_swap_price": 10.2148,
                "buy_swap_price": 10.2149,
                "remark_th": " ",
                "remark_en": " ",
                "last_upd_date": "2025-11-12T16:10:36.647"
            },
            {
                "nav_date": "2025-11-10",
                "unique_id": "C0000005025",
                "class_abbr_name": "KKP GBA-UI-M",
                "net_asset": 4912787968,
                "last_val": 10.2972,
                "previous_val": 0,
                "sell_price": 10.2973,
                "buy_price": 10.2972,
                "sell_swap_price": 10.2972,
                "buy_swap_price": 10.2973,
                "remark_th": " ",
                "remark_en": " ",
                "last_upd_date": "2025-11-14T16:58:54.717"
            },
            {
                "nav_date": "2025-11-17",
                "unique_id": "C0000005025",
                "class_abbr_name": "KKP GBA-UI-M",
                "net_asset": 4986387456,
                "last_val": 10.2152,
                "previous_val": 0,
                "sell_price": 10.2153,
                "buy_price": 10.2152,
                "sell_swap_price": 10.2152,
                "buy_swap_price": 10.2153,
                "remark_th": " ",
                "remark_en": " ",
                "last_upd_date": "2025-11-20T15:06:42.74"
            },
            {
                "nav_date": "2025-11-18",
                "unique_id": "C0000005025",
                "class_abbr_name": "KKP GBA-UI-M",
                "net_asset": 4944670208,
                "last_val": 10.1298,
                "previous_val": 0,
                "sell_price": 10.1299,
                "buy_price": 10.1298,
                "sell_swap_price": 10.1298,
                "buy_swap_price": 10.1299,
                "remark_th": " ",
                "remark_en": " ",
                "last_upd_date": "2025-11-21T15:05:30.35"
            },
            {
                "nav_date": "2025-11-19",
                "unique_id": "C0000005025",
                "class_abbr_name": "KKP GBA-UI-M",
                "net_asset": 4956026880,
                "last_val": 10.153,
                "previous_val": 0,
                "sell_price": 10.1531,
                "buy_price": 10.153,
                "sell_swap_price": 10.153,
                "buy_swap_price": 10.1531,
                "remark_th": " ",
                "remark_en": " ",
                "last_upd_date": "2025-11-24T15:04:34.813"
            },
            {
                "nav_date": "2025-11-20",
                "unique_id": "C0000005025",
                "class_abbr_name": "KKP GBA-UI-M",
                "net_asset": 5707719680,
                "last_val": 10.133,
                "previous_val": 0,
                "sell_price": 10.1331,
                "buy_price": 10.133,
                "sell_swap_price": 10.133,
                "buy_swap_price": 10.1331,
                "remark_th": " ",
                "remark_en": " ",
                "last_upd_date": "2025-11-25T15:08:18.467"
            },
            {
                "nav_date": "2025-11-21",
                "unique_id": "C0000005025",
                "class_abbr_name": "KKP GBA-UI-M",
                "net_asset": 5765032448,
                "last_val": 10.1215,
                "previous_val": 0,
                "sell_price": 10.1216,
                "buy_price": 10.1215,
                "sell_swap_price": 10.1215,
                "buy_swap_price": 10.1216,
                "remark_th": " ",
                "remark_en": " ",
                "last_upd_date": "2025-11-27T15:10:36.143"
            },
            {
                "nav_date": "2025-11-25",
                "unique_id": "C0000005025",
                "class_abbr_name": "KKP GBA-UI-M",
                "net_asset": 5901067776,
                "last_val": 10.2538,
                "previous_val": 0,
                "sell_price": 10.2539,
                "buy_price": 10.2538,
                "sell_swap_price": 10.2538,
                "buy_swap_price": 10.2539,
                "remark_th": " ",
                "remark_en": " ",
                "last_upd_date": "2025-11-28T15:09:33.727"
            },
            {
                "nav_date": "2025-11-26",
                "unique_id": "C0000005025",
                "class_abbr_name": "KKP GBA-UI-M",
                "net_asset": 5949803008,
                "last_val": 10.3088,
                "previous_val": 0,
                "sell_price": 10.3089,
                "buy_price": 10.3088,
                "sell_swap_price": 10.3088,
                "buy_swap_price": 10.3089,
                "remark_th": " ",
                "remark_en": " ",
                "last_upd_date": "2025-11-30T07:09:45.723"
            }
        ]
    }
}