{
    "lastUpdate": 1737185106712,
    "nextUpdate": 1737270964609,
    "data": {
        "lastNav": "2025-01-16",
        "fund": {
            "proj_id": "M0965_2567",
            "regis_id": "MF0702_2567",
            "regis_date": "2024-12-04",
            "cancel_date": "-",
            "proj_name_th": "กองทุนเปิดเคเคพี US500 EQUAL WEIGHT - UNHEDGED",
            "proj_name_en": "KKP US500 EQUAL WEIGHT FUND - UNHEDGED",
            "proj_abbr_name": "KKP EWUS500-UH FUND",
            "fund_status": "RG",
            "unique_id": "C0000005025",
            "permit_us_investment": null,
            "invest_country_flag": "1",
            "last_upd_date": "2025-01-18T08:02:06.097"
        },
        "navs": [
            {
                "nav_date": "2024-12-23",
                "unique_id": "C0000005025",
                "class_abbr_name": "KKP EWUS500-UH-M",
                "net_asset": 0,
                "last_val": 9.3725,
                "previous_val": 0,
                "sell_price": 9.3726,
                "buy_price": 9.3725,
                "sell_swap_price": 9.3725,
                "buy_swap_price": 9.3726,
                "remark_th": " ",
                "remark_en": " ",
                "last_upd_date": "2024-12-25T16:07:06.77"
            },
            {
                "nav_date": "2024-12-24",
                "unique_id": "C0000005025",
                "class_abbr_name": "KKP EWUS500-UH-M",
                "net_asset": 0,
                "last_val": 9.4358,
                "previous_val": 0,
                "sell_price": 9.4359,
                "buy_price": 9.4358,
                "sell_swap_price": 9.4358,
                "buy_swap_price": 9.4359,
                "remark_th": " ",
                "remark_en": " ",
                "last_upd_date": "2024-12-27T16:08:53.23"
            },
            {
                "nav_date": "2024-12-26",
                "unique_id": "C0000005025",
                "class_abbr_name": "KKP EWUS500-UH-M",
                "net_asset": 0,
                "last_val": 9.4783,
                "previous_val": 0,
                "sell_price": 9.4784,
                "buy_price": 9.4783,
                "sell_swap_price": 9.4783,
                "buy_swap_price": 9.4784,
                "remark_th": " ",
                "remark_en": " ",
                "last_upd_date": "2024-12-28T16:06:42.577"
            },
            {
                "nav_date": "2024-12-30",
                "unique_id": "C0000005025",
                "class_abbr_name": "KKP EWUS500-UH-M",
                "net_asset": 0,
                "last_val": 9.2796,
                "previous_val": 0,
                "sell_price": 9.2797,
                "buy_price": 9.2796,
                "sell_swap_price": 9.2796,
                "buy_swap_price": 9.2797,
                "remark_th": " ",
                "remark_en": " ",
                "last_upd_date": "2025-01-03T16:07:08.173"
            },
            {
                "nav_date": "2025-01-02",
                "unique_id": "C0000005025",
                "class_abbr_name": "KKP EWUS500-UH-M",
                "net_asset": 0,
                "last_val": 9.312,
                "previous_val": 0,
                "sell_price": 9.3121,
                "buy_price": 9.312,
                "sell_swap_price": 9.312,
                "buy_swap_price": 9.3121,
                "remark_th": " ",
                "remark_en": " ",
                "last_upd_date": "2025-01-06T16:07:14.93"
            },
            {
                "nav_date": "2025-01-03",
                "unique_id": "C0000005025",
                "class_abbr_name": "KKP EWUS500-UH-M",
                "net_asset": 0,
                "last_val": 9.4616,
                "previous_val": 0,
                "sell_price": 9.4617,
                "buy_price": 9.4616,
                "sell_swap_price": 9.4616,
                "buy_swap_price": 9.4617,
                "remark_th": " ",
                "remark_en": " ",
                "last_upd_date": "2025-01-07T16:03:32.95"
            },
            {
                "nav_date": "2025-01-06",
                "unique_id": "C0000005025",
                "class_abbr_name": "KKP EWUS500-UH-M",
                "net_asset": 0,
                "last_val": 9.4864,
                "previous_val": 0,
                "sell_price": 9.4865,
                "buy_price": 9.4864,
                "sell_swap_price": 9.4864,
                "buy_swap_price": 9.4865,
                "remark_th": " ",
                "remark_en": " ",
                "last_upd_date": "2025-01-08T16:08:06.317"
            },
            {
                "nav_date": "2025-01-07",
                "unique_id": "C0000005025",
                "class_abbr_name": "KKP EWUS500-UH-M",
                "net_asset": 0,
                "last_val": 9.4263,
                "previous_val": 0,
                "sell_price": 9.4264,
                "buy_price": 9.4263,
                "sell_swap_price": 9.4263,
                "buy_swap_price": 9.4264,
                "remark_th": " ",
                "remark_en": " ",
                "last_upd_date": "2025-01-09T16:05:00.623"
            },
            {
                "nav_date": "2025-01-08",
                "unique_id": "C0000005025",
                "class_abbr_name": "KKP EWUS500-UH-M",
                "net_asset": 0,
                "last_val": 9.4713,
                "previous_val": 0,
                "sell_price": 9.4714,
                "buy_price": 9.4713,
                "sell_swap_price": 9.4713,
                "buy_swap_price": 9.4714,
                "remark_th": " ",
                "remark_en": " ",
                "last_upd_date": "2025-01-13T16:07:28.987"
            },
            {
                "nav_date": "2025-01-10",
                "unique_id": "C0000005025",
                "class_abbr_name": "KKP EWUS500-UH-M",
                "net_asset": 0,
                "last_val": 9.3241,
                "previous_val": 0,
                "sell_price": 9.3242,
                "buy_price": 9.3241,
                "sell_swap_price": 9.3241,
                "buy_swap_price": 9.3242,
                "remark_th": " ",
                "remark_en": " ",
                "last_upd_date": "2025-01-14T16:06:39.33"
            },
            {
                "nav_date": "2025-01-13",
                "unique_id": "C0000005025",
                "class_abbr_name": "KKP EWUS500-UH-M",
                "net_asset": 0,
                "last_val": 9.4501,
                "previous_val": 0,
                "sell_price": 9.4502,
                "buy_price": 9.4501,
                "sell_swap_price": 9.4501,
                "buy_swap_price": 9.4502,
                "remark_th": " ",
                "remark_en": " ",
                "last_upd_date": "2025-01-15T21:06:59.313"
            },
            {
                "nav_date": "2025-01-14",
                "unique_id": "C0000005025",
                "class_abbr_name": "KKP EWUS500-UH-M",
                "net_asset": 0,
                "last_val": 9.5042,
                "previous_val": 0,
                "sell_price": 9.5043,
                "buy_price": 9.5042,
                "sell_swap_price": 9.5042,
                "buy_swap_price": 9.5043,
                "remark_th": " ",
                "remark_en": " ",
                "last_upd_date": "2025-01-16T16:07:18.267"
            },
            {
                "nav_date": "2025-01-15",
                "unique_id": "C0000005025",
                "class_abbr_name": "KKP EWUS500-UH-M",
                "net_asset": 0,
                "last_val": 9.6066,
                "previous_val": 0,
                "sell_price": 9.6067,
                "buy_price": 9.6066,
                "sell_swap_price": 9.6066,
                "buy_swap_price": 9.6067,
                "remark_th": " ",
                "remark_en": " ",
                "last_upd_date": "2025-01-17T16:04:47.73"
            },
            {
                "nav_date": "2025-01-16",
                "unique_id": "C0000005025",
                "class_abbr_name": "KKP EWUS500-UH-M",
                "net_asset": 0,
                "last_val": 9.6341,
                "previous_val": 0,
                "sell_price": 9.6342,
                "buy_price": 9.6341,
                "sell_swap_price": 9.6341,
                "buy_swap_price": 9.6342,
                "remark_th": " ",
                "remark_en": " ",
                "last_upd_date": "2025-01-18T08:08:32.363"
            }
        ]
    }
}