{
    "lastUpdate": 1722101931806,
    "nextUpdate": 1722188075571,
    "data": {
        "lastNav": "2024-07-24",
        "fund": {
            "proj_id": "M0501_2566",
            "regis_id": "MF0360_2566",
            "regis_date": "2023-09-14",
            "cancel_date": "-",
            "proj_name_th": "กองทุนเปิดเคเคพี พาสซีฟ โกลบอล อิควิตี้ อันเฮดจ์",
            "proj_name_en": "KKP PASSIVE GLOBAL EQUITY FUND - UNHEDGED",
            "proj_abbr_name": "KKP PGE-UH FUND",
            "fund_status": "RG",
            "unique_id": "C0000005025",
            "permit_us_investment": null,
            "invest_country_flag": "1",
            "last_upd_date": "2024-07-27T07:02:17.43"
        },
        "navs": [
            {
                "nav_date": "2024-07-15",
                "unique_id": "C0000005025",
                "class_abbr_name": "KKP PGE-UH",
                "net_asset": 1199117407.45,
                "last_val": 12.2532,
                "previous_val": 0,
                "sell_price": 12.2533,
                "buy_price": 12.2532,
                "sell_swap_price": 12.2532,
                "buy_swap_price": 12.2533,
                "remark_th": " ",
                "remark_en": " ",
                "last_upd_date": "2024-07-17T08:04:04.493"
            },
            {
                "nav_date": "2024-07-16",
                "unique_id": "C0000005025",
                "class_abbr_name": "KKP PGE-UH",
                "net_asset": 1209138830.94,
                "last_val": 12.2915,
                "previous_val": 0,
                "sell_price": 12.2916,
                "buy_price": 12.2915,
                "sell_swap_price": 12.2915,
                "buy_swap_price": 12.2916,
                "remark_th": " ",
                "remark_en": " ",
                "last_upd_date": "2024-07-18T08:22:27.287"
            },
            {
                "nav_date": "2024-07-17",
                "unique_id": "C0000005025",
                "class_abbr_name": "KKP PGE-UH",
                "net_asset": 1196849760.59,
                "last_val": 12.0335,
                "previous_val": 0,
                "sell_price": 12.0336,
                "buy_price": 12.0335,
                "sell_swap_price": 12.0335,
                "buy_swap_price": 12.0336,
                "remark_th": " ",
                "remark_en": " ",
                "last_upd_date": "2024-07-19T08:44:31.75"
            },
            {
                "nav_date": "2024-07-18",
                "unique_id": "C0000005025",
                "class_abbr_name": "KKP PGE-UH",
                "net_asset": 1210467437.96,
                "last_val": 11.9771,
                "previous_val": 0,
                "sell_price": 11.9772,
                "buy_price": 11.9771,
                "sell_swap_price": 11.9771,
                "buy_swap_price": 11.9772,
                "remark_th": " ",
                "remark_en": " ",
                "last_upd_date": "2024-07-23T08:24:54.193"
            },
            {
                "nav_date": "2024-07-19",
                "unique_id": "C0000005025",
                "class_abbr_name": "KKP PGE-UH",
                "net_asset": 1222849938.64,
                "last_val": 11.993,
                "previous_val": 0,
                "sell_price": 11.9931,
                "buy_price": 11.993,
                "sell_swap_price": 11.993,
                "buy_swap_price": 11.9931,
                "remark_th": " ",
                "remark_en": " ",
                "last_upd_date": "2024-07-24T07:27:34.293"
            },
            {
                "nav_date": "2024-07-23",
                "unique_id": "C0000005025",
                "class_abbr_name": "KKP PGE-UH",
                "net_asset": 1244285010.38,
                "last_val": 12.0633,
                "previous_val": 0,
                "sell_price": 12.0634,
                "buy_price": 12.0633,
                "sell_swap_price": 12.0633,
                "buy_swap_price": 12.0634,
                "remark_th": " ",
                "remark_en": " ",
                "last_upd_date": "2024-07-25T07:41:44.45"
            },
            {
                "nav_date": "2024-07-24",
                "unique_id": "C0000005025",
                "class_abbr_name": "KKP PGE-UH",
                "net_asset": 1296962262.41,
                "last_val": 11.8109,
                "previous_val": 0,
                "sell_price": 11.811,
                "buy_price": 11.8109,
                "sell_swap_price": 11.8109,
                "buy_swap_price": 11.811,
                "remark_th": " ",
                "remark_en": " ",
                "last_upd_date": "2024-07-26T09:06:17.367"
            }
        ]
    }
}