{
    "lastUpdate": 1722101830094,
    "nextUpdate": 1722188075571,
    "data": {
        "lastNav": "2024-07-25",
        "fund": {
            "proj_id": "M0078_2559",
            "regis_id": "MF0124_2559",
            "regis_date": "2016-03-23",
            "cancel_date": "-",
            "proj_name_th": "กองทุนเปิดเคเคพี สมาร์ท มินิมั่ม โวลาติลิตี้",
            "proj_name_en": "KKP SMART MINIMUM VOLATILITY FUND",
            "proj_abbr_name": "KKP SMART MV FUND",
            "fund_status": "RG",
            "unique_id": "C0000005025",
            "permit_us_investment": null,
            "invest_country_flag": "3",
            "last_upd_date": "2024-07-27T07:02:17.43"
        },
        "navs": [
            {
                "nav_date": "2024-07-15",
                "unique_id": "C0000005025",
                "class_abbr_name": "KKP SMART MV",
                "net_asset": 138392481.31,
                "last_val": 10.3967,
                "previous_val": 0,
                "sell_price": 10.3968,
                "buy_price": 10.3967,
                "sell_swap_price": 10.3967,
                "buy_swap_price": 10.3968,
                "remark_th": " ",
                "remark_en": " ",
                "last_upd_date": "2024-07-16T09:00:21.347"
            },
            {
                "nav_date": "2024-07-16",
                "unique_id": "C0000005025",
                "class_abbr_name": "KKP SMART MV",
                "net_asset": 137411880.34,
                "last_val": 10.3237,
                "previous_val": 0,
                "sell_price": 10.3238,
                "buy_price": 10.3237,
                "sell_swap_price": 10.3237,
                "buy_swap_price": 10.3238,
                "remark_th": " ",
                "remark_en": " ",
                "last_upd_date": "2024-07-17T08:04:04.493"
            },
            {
                "nav_date": "2024-07-17",
                "unique_id": "C0000005025",
                "class_abbr_name": "KKP SMART MV",
                "net_asset": 137278923.22,
                "last_val": 10.3137,
                "previous_val": 0,
                "sell_price": 10.3138,
                "buy_price": 10.3137,
                "sell_swap_price": 10.3137,
                "buy_swap_price": 10.3138,
                "remark_th": " ",
                "remark_en": " ",
                "last_upd_date": "2024-07-18T08:22:27.287"
            },
            {
                "nav_date": "2024-07-18",
                "unique_id": "C0000005025",
                "class_abbr_name": "KKP SMART MV",
                "net_asset": 138418055.57,
                "last_val": 10.3995,
                "previous_val": 0,
                "sell_price": 10.3996,
                "buy_price": 10.3995,
                "sell_swap_price": 10.3995,
                "buy_swap_price": 10.3996,
                "remark_th": " ",
                "remark_en": " ",
                "last_upd_date": "2024-07-19T08:44:31.75"
            },
            {
                "nav_date": "2024-07-19",
                "unique_id": "C0000005025",
                "class_abbr_name": "KKP SMART MV",
                "net_asset": 137762530.59,
                "last_val": 10.35,
                "previous_val": 0,
                "sell_price": 10.3501,
                "buy_price": 10.35,
                "sell_swap_price": 10.35,
                "buy_swap_price": 10.3501,
                "remark_th": " ",
                "remark_en": " ",
                "last_upd_date": "2024-07-23T08:24:54.193"
            },
            {
                "nav_date": "2024-07-23",
                "unique_id": "C0000005025",
                "class_abbr_name": "KKP SMART MV",
                "net_asset": 136280823.22,
                "last_val": 10.2383,
                "previous_val": 0,
                "sell_price": 10.2384,
                "buy_price": 10.2383,
                "sell_swap_price": 10.2383,
                "buy_swap_price": 10.2384,
                "remark_th": " ",
                "remark_en": " ",
                "last_upd_date": "2024-07-24T07:27:34.293"
            },
            {
                "nav_date": "2024-07-24",
                "unique_id": "C0000005025",
                "class_abbr_name": "KKP SMART MV",
                "net_asset": 135695903.25,
                "last_val": 10.1939,
                "previous_val": 0,
                "sell_price": 10.194,
                "buy_price": 10.1939,
                "sell_swap_price": 10.1939,
                "buy_swap_price": 10.194,
                "remark_th": " ",
                "remark_en": " ",
                "last_upd_date": "2024-07-25T07:41:44.45"
            },
            {
                "nav_date": "2024-07-25",
                "unique_id": "C0000005025",
                "class_abbr_name": "KKP SMART MV",
                "net_asset": 135164993.18,
                "last_val": 10.154,
                "previous_val": 0,
                "sell_price": 10.1541,
                "buy_price": 10.154,
                "sell_swap_price": 10.154,
                "buy_swap_price": 10.1541,
                "remark_th": " ",
                "remark_en": " ",
                "last_upd_date": "2024-07-26T09:06:17.367"
            }
        ]
    }
}